pomo_fish_powerline/__init__.py
pomo_fish_powerline/segments.py
pomo_fish_powerline-0.1.0.dist-info/LICENSE
pomo_fish_powerline-0.1.0.dist-info/METADATA
pomo_fish_powerline-0.1.0.dist-info/WHEEL
pomo_fish_powerline-0.1.0.dist-info/top_level.txt
pomo_fish_powerline-0.1.0.dist-info/RECORD
