Metadata-Version: 2.1
Name: pomo-fish-powerline
Version: 0.1.0
Summary: A Powerline segment to display the Pomodoro timer from pomo.fish
Author-email: Jon Cinque <me@jonc.dev>
Project-URL: Homepage, https://github.com/joncinque/pomo.fish/powerline
Project-URL: Bug Tracker, https://github.com/joncinque/pomo.fish/issues
Classifier: Programming Language :: Python :: 3
Classifier: License :: OSI Approved :: MIT License
Classifier: Operating System :: OS Independent
Requires-Python: >=3.7
License-File: LICENSE
